sections/__init__.py
sections/attr_parser.py
sections/dict.py
sections/meta.py
sections/node.py
sections/pluralizer.py
sections/section.py
sections/string_parser.py
sections/types.py
sections-0.0.3.dist-info/AUTHORS.rst
sections-0.0.3.dist-info/LICENSE
sections-0.0.3.dist-info/METADATA
sections-0.0.3.dist-info/WHEEL
sections-0.0.3.dist-info/top_level.txt
sections-0.0.3.dist-info/RECORD
