Metadata-Version: 2.1
Name: sections
Version: 0.0.3
Summary: Flexible tree data structures for organizing lists and dicts into sections.
Home-page: https://github.com/trevorpogue/sections
Author: Trevor Edwin Pogue
Author-email: trevorpogue@gmail.com
License: MIT
Project-URL: Documentation, https://sections.readthedocs.io/
Project-URL: Changelog, https://sections.readthedocs.io/en/latest/changelog.html
Project-URL: Issue Tracker, https://github.com/trevorpogue/sections/issues
Keywords: tree,data,structure,organize,section,category,attr,dict,list,node,vertex,graph
Platform: UNKNOWN
Classifier: Development Status :: 5 - Production/Stable
Classifier: Intended Audience :: Developers
Classifier: License :: OSI Approved :: MIT License
Classifier: Operating System :: Unix
Classifier: Operating System :: POSIX
Classifier: Operating System :: Microsoft :: Windows
Classifier: Programming Language :: Python
Classifier: Programming Language :: Python :: 3
Classifier: Programming Language :: Python :: 3 :: Only
Classifier: Programming Language :: Python :: 3.6
Classifier: Programming Language :: Python :: 3.7
Classifier: Programming Language :: Python :: 3.8
Classifier: Programming Language :: Python :: 3.9
Classifier: Programming Language :: Python :: Implementation :: CPython
Classifier: Topic :: Utilities
Requires-Python: >=3.6
Requires-Dist: pluralizer (>=0.0.0)
